alldata/__init__.py
alldata/__main__.py
alldata/cli.py
alldata-0.2.0.dist-info/AUTHORS.rst
alldata-0.2.0.dist-info/LICENSE
alldata-0.2.0.dist-info/METADATA
alldata-0.2.0.dist-info/WHEEL
alldata-0.2.0.dist-info/dependency_links.txt
alldata-0.2.0.dist-info/entry_points.txt
alldata-0.2.0.dist-info/top_level.txt
alldata-0.2.0.dist-info/RECORD
