Metadata-Version: 2.1
Name: alldata
Version: 0.2.0
Summary: This is a Package in which you can Extract Images,Text and Tables from 1 package
Home-page: https://github.com/shehrozkapoor/alldata.git
Author: shehrozkapoor
Author-email: shehrozkapoor@gmail.com
License: BSD-2-Clause
Project-URL: Issue Tracker, https://https://github.com/shehrozkapoor/alldata.git/shehrozkapoor/python-alldata/issues
Project-URL: Documentation, https://python-alldata.readthedocs.io/
Project-URL: Changelog, https://python-alldata.readthedocs.io/en/latest/changelog.html
Keywords: extractImages,extractTable,extractText
Platform: UNKNOWN
Classifier: Development Status :: 5 - Production/Stable
Classifier: Intended Audience :: Developers
Classifier: License :: OSI Approved :: BSD License
Classifier: Operating System :: Unix
Classifier: Operating System :: POSIX
Classifier: Operating System :: Microsoft :: Windows
Classifier: Programming Language :: Python
Classifier: Programming Language :: Python :: 2.7
Classifier: Programming Language :: Python :: 3
Classifier: Programming Language :: Python :: 3.5
Classifier: Programming Language :: Python :: 3.6
Classifier: Programming Language :: Python :: 3.7
Classifier: Programming Language :: Python :: 3.8
Classifier: Programming Language :: Python :: 3.9
Classifier: Programming Language :: Python :: Implementation :: CPython
Classifier: Programming Language :: Python :: Implementation :: PyPy
Classifier: Topic :: Utilities
Requires-Python: >=2.7, !=3.0.*, !=3.1.*, !=3.2.*, !=3.3.*, !=3.4.*
Requires-Dist: pip
Requires-Dist: tabula-py
Requires-Dist: camelot-py[cv]
Requires-Dist: PyPDF2
Requires-Dist: PyMuPDF
Requires-Dist: pillow
Requires-Dist: numpy
Requires-Dist: spacy
Requires-Dist: pdfminer
Requires-Dist: pdfminer.six
